spetslogging/__init__.py
spetslogging/logger.py
spetslogging-0.0.1.dist-info/LICENSE
spetslogging-0.0.1.dist-info/METADATA
spetslogging-0.0.1.dist-info/WHEEL
spetslogging-0.0.1.dist-info/top_level.txt
spetslogging-0.0.1.dist-info/RECORD
