Metadata-Version: 2.1
Name: spetslogging
Version: 0.0.1
Summary: SpetsLogging is a simple way to log in the console and in a file.
Home-page: https://github.com/DiNAMitiON/SpetsLoging
Author: Dmitry Goncharov (_DiNAMitiON_)
Author-email: dinamition42@gmail.com
Project-URL: SpetsDevelopers | Support, https://discord.gg/z5hEVQ5agn/
Project-URL: Source Code, https://github.com/DiNAMitiON/SpetsLoging/
Keywords: Logging,write to file
Classifier: Programming Language :: Python :: 3
Classifier: License :: OSI Approved :: MIT License
Classifier: Operating System :: OS Independent
Requires-Python: >=3.7
License-File: LICENSE
Requires-Dist: colorama ==0.4.6
